pymsbt/__init__.py
pymsbt/classes.py
pymsbt/msbt_read.py
pymsbt/msbt_write.py
pymsbt-1.0.11.dist-info/LICENSE
pymsbt-1.0.11.dist-info/METADATA
pymsbt-1.0.11.dist-info/WHEEL
pymsbt-1.0.11.dist-info/top_level.txt
pymsbt-1.0.11.dist-info/RECORD
