Metadata-Version: 2.1
Name: pymsbt
Version: 1.0.11
Summary: A python library for parsing and editing .msbt binary files
Home-page: https://github.com/p1gyy/pymsbt
Author: Piggy Gaming
Requires-Python: >=3.12
License-File: LICENSE
